{"meta":{"created_at":"2021/07/10 11:27:17","elapsed_s":7.0411019999999995,"judge":{"dislikes":10262,"fit_in_hole":true,"gained_bonuses":[],"is_valid":true,"satisfy_stretch":true},"solver":"FlipAnnealingSolver"},"vertices":[[17,57],[46,38],[22,31],[24,36],[27,55],[42,64],[24,39],[19,42],[36,26],[25,29],[33,42],[40,49],[38,41],[18,43],[40,40],[36,43],[31,43],[34,35],[20,29],[49,44],[42,50],[41,45],[24,41],[56,44],[46,44],[36,50],[34,31],[35,42],[34,42],[62,31],[37,57],[20,54],[72,37],[25,46],[8,31],[8,60]]}