{"bonuses":[],"meta":{"created_at":"2021/07/12 14:59:59","elapsed_s":106.806888,"git_commit":"d3e663482e1466b43a1c743a2bb622e17c6ec653","judge":{"dislikes":289,"fit_in_hole":true,"gained_bonuses":[],"is_valid":true,"satisfy_stretch":true},"solver":"RandomRestartSolver"},"vertices":[[14,10],[9,7],[24,10],[36,18],[16,16],[49,7],[66,10],[65,8],[34,8],[57,11],[62,12],[15,25],[72,7],[70,21],[72,22],[22,26],[64,11],[68,15],[6,24],[29,25],[66,25],[11,24],[59,17],[23,36],[52,33],[52,35],[51,37],[27,49],[54,37],[54,50],[56,51],[52,41],[50,41],[57,50],[52,46],[60,56],[50,50],[19,57],[31,56]]}